intugle/__init__.py
intugle/cli.py
intugle/data_product.py
intugle/semantic_model.py
intugle/semantic_search.py
intugle/adapters/__init__.py
intugle/adapters/adapter.py
intugle/adapters/factory.py
intugle/adapters/models.py
intugle/adapters/utils.py
intugle/adapters/common/models.py
intugle/adapters/common/relationships.py
intugle/adapters/types/bigquery/__init__.py
intugle/adapters/types/bigquery/bigquery.py
intugle/adapters/types/bigquery/models.py
intugle/adapters/types/databricks/databricks.py
intugle/adapters/types/databricks/models.py
intugle/adapters/types/duckdb/duckdb.py
intugle/adapters/types/duckdb/models.py
intugle/adapters/types/mariadb/__init__.py
intugle/adapters/types/mariadb/mariadb.py
intugle/adapters/types/mariadb/models.py
intugle/adapters/types/mysql/__init__.py
intugle/adapters/types/mysql/models.py
intugle/adapters/types/mysql/mysql.py
intugle/adapters/types/oracle/__init__.py
intugle/adapters/types/oracle/models.py
intugle/adapters/types/oracle/oracle.py
intugle/adapters/types/pandas/pandas.py
intugle/adapters/types/postgres/__init__.py
intugle/adapters/types/postgres/models.py
intugle/adapters/types/postgres/postgres.py
intugle/adapters/types/snowflake/models.py
intugle/adapters/types/snowflake/snowflake.py
intugle/adapters/types/sqlite/__init__.py
intugle/adapters/types/sqlite/models.py
intugle/adapters/types/sqlite/sqlite.py
intugle/adapters/types/sqlserver/__init__.py
intugle/adapters/types/sqlserver/models.py
intugle/adapters/types/sqlserver/sqlserver.py
intugle/analysis/__init__.py
intugle/analysis/models.py
intugle/artifacts/dependant/datatype_l1_identification/en-80k.txt
intugle/artifacts/model_objects/datatype_l1_identification/di_l1_classifier_encoder_13052023.pkl
intugle/artifacts/model_objects/datatype_l1_identification/di_l1_classifier_xgb_13052023.pkl
intugle/common/schema.py
intugle/common/exception/errors.py
intugle/common/resources/base.py
intugle/common/resources/types.py
intugle/core/__init__.py
intugle/core/console.py
intugle-1.3.0.dist-info/licenses/LICENSE
intugle-1.3.0.dist-info/licenses/NOTICE
intugle-1.3.0.dist-info/METADATA
intugle-1.3.0.dist-info/WHEEL
intugle-1.3.0.dist-info/entry_points.txt
intugle-1.3.0.dist-info/top_level.txt
intugle-1.3.0.dist-info/RECORD
