Metadata-Version: 2.4
Name: intugle
Version: 1.3.0
Summary: A GenAI-powered Python library for building semantic layers.
Author-email: Intugle <hello@intugle.ai>
License: Apache-2.0
Project-URL: Homepage, https://github.com/Intugle/data-tools
Project-URL: Bug Tracker, https://github.com/Intugle/data-tools/issues
Keywords: data,semantic layer,genai,llm,data profiling,link prediction,sql generation
Classifier: Programming Language :: Python :: 3
Classifier: License :: OSI Approved :: Apache Software License
Classifier: Operating System :: OS Independent
Classifier: Development Status :: 3 - Alpha
Classifier: Intended Audience :: Developers
Classifier: Intended Audience :: Science/Research
Classifier: Topic :: Scientific/Engineering :: Artificial Intelligence
Classifier: Topic :: Software Development :: Libraries :: Python Modules
Requires-Python: >=3.10
License-File: LICENSE
License-File: NOTICE
Requires-Dist: langchain-community<1.0.0,>=0.3.21
Requires-Dist: langchain-openai<1.0.0,>=0.3.28
Requires-Dist: langgraph<1.0.0,>=0.6.9
Requires-Dist: nltk>=3.9.1
Requires-Dist: numpy<=2.3.0
Requires-Dist: asyncpg>=0.30.0
Requires-Dist: fastapi[standard]>=0.116.1
Requires-Dist: matplotlib>=3.10.5
Requires-Dist: mcp[cli]>=1.12.4
Requires-Dist: networkx>=3.4.2
Requires-Dist: pandas>=2.2.2
Requires-Dist: pyaml>=25.7.0
Requires-Dist: pydantic>=2.11.7
Requires-Dist: pydantic-settings>=2.10.1
Requires-Dist: pyfunctional>=1.5.0
Requires-Dist: python-dotenv>=1.1.1
Requires-Dist: symspellpy>=6.9.0
Requires-Dist: trieregex>=1.0.0
Requires-Dist: xgboost>=3.0.4
Requires-Dist: pyyaml>=6.0.2
Requires-Dist: duckdb>=1.3.2
Requires-Dist: scikit-learn==1.7.1
Requires-Dist: langchain[anthropic,google-genai,openai]<1.0.0,>=0.3.27
Requires-Dist: qdrant-client>=1.15.1
Requires-Dist: rich>=14.1.0
Requires-Dist: aiohttp>=3.9.5
Requires-Dist: aiofiles>=23.2.1
Requires-Dist: tavily-python>=0.1.11
Provides-Extra: snowflake
Requires-Dist: snowflake-snowpark-python[pandas]>=1.12.0; extra == "snowflake"
Requires-Dist: sqlglot>=27.20.0; extra == "snowflake"
Provides-Extra: databricks
Requires-Dist: databricks-sql-connector>=4.1.3; extra == "databricks"
Requires-Dist: pyspark<4.0.0,>=3.5.0; extra == "databricks"
Requires-Dist: sqlglot>=27.20.0; extra == "databricks"
Provides-Extra: postgres
Requires-Dist: asyncpg>=0.30.0; extra == "postgres"
Requires-Dist: sqlglot>=27.20.0; extra == "postgres"
Provides-Extra: bigquery
Requires-Dist: google-cloud-bigquery>=3.11.0; extra == "bigquery"
Requires-Dist: sqlglot>=27.20.0; extra == "bigquery"
Provides-Extra: sqlserver
Requires-Dist: mssql-python>=0.13.1; extra == "sqlserver"
Requires-Dist: sqlglot>=27.20.0; extra == "sqlserver"
Provides-Extra: mysql
Requires-Dist: PyMySQL>=1.1.0; extra == "mysql"
Requires-Dist: sqlglot>=27.20.0; extra == "mysql"
Provides-Extra: mariadb
Requires-Dist: mariadb>=1.1.10; extra == "mariadb"
Requires-Dist: sqlglot>=27.20.0; extra == "mariadb"
Provides-Extra: oracle
Requires-Dist: oracledb>=2.0.0; extra == "oracle"
Requires-Dist: sqlglot>=27.20.0; extra == "oracle"
Provides-Extra: streamlit
Requires-Dist: streamlit==1.50.0; extra == "streamlit"
Requires-Dist: pyngrok==7.4.0; extra == "streamlit"
Requires-Dist: python-dotenv==1.1.1; extra == "streamlit"
Requires-Dist: xlsxwriter==3.2.9; extra == "streamlit"
Requires-Dist: plotly; extra == "streamlit"
Requires-Dist: graphviz; extra == "streamlit"
Dynamic: license-file
